gnomad_db/__init__.py
gnomad_db/database.py
gnomad_db/utils.py
gnomad_db/pkgdata/gnomad_columns.yaml
gnomad_db-0.1.6.dist-info/licenses/LICENSE
gnomad_db-0.1.6.dist-info/METADATA
gnomad_db-0.1.6.dist-info/WHEEL
gnomad_db-0.1.6.dist-info/top_level.txt
gnomad_db-0.1.6.dist-info/RECORD
