Metadata-Version: 2.4
Name: gnomad_db
Version: 0.1.6
Summary: This package scales the huge gnomAD files to a SQLite database, which is easy and fast to query. It extracts from a gnomAD vcf the minor allele frequency for each variant.
Home-page: https://github.com/KalinNonchev/gnomAD_DB
Author: KalinNonchev
Author-email: boo@foo.com
License: MIT License
Requires-Python: >=3.8
License-File: LICENSE
Requires-Dist: pandas
Requires-Dist: numpy
Requires-Dist: joblib
Requires-Dist: tqdm
Requires-Dist: pyyaml
Dynamic: author
Dynamic: author-email
Dynamic: description
Dynamic: description-content-type
Dynamic: home-page
Dynamic: license
Dynamic: license-file
Dynamic: requires-dist
Dynamic: requires-python
Dynamic: summary
